odoo/addons/stock_orderpoint_origin_mrp_link/README.rst
odoo/addons/stock_orderpoint_origin_mrp_link/__init__.py
odoo/addons/stock_orderpoint_origin_mrp_link/__manifest__.py
odoo/addons/stock_orderpoint_origin_mrp_link/i18n/it.po
odoo/addons/stock_orderpoint_origin_mrp_link/i18n/stock_orderpoint_origin_mrp_link.pot
odoo/addons/stock_orderpoint_origin_mrp_link/models/__init__.py
odoo/addons/stock_orderpoint_origin_mrp_link/models/purchase_order.py
odoo/addons/stock_orderpoint_origin_mrp_link/readme/CONTRIBUTORS.rst
odoo/addons/stock_orderpoint_origin_mrp_link/readme/DESCRIPTION.rst
odoo/addons/stock_orderpoint_origin_mrp_link/readme/USAGE.rst
odoo/addons/stock_orderpoint_origin_mrp_link/static/description/icon.png
odoo/addons/stock_orderpoint_origin_mrp_link/static/description/index.html
odoo14_addon_stock_orderpoint_origin_mrp_link-14.0.1.0.1.dev5.dist-info/METADATA
odoo14_addon_stock_orderpoint_origin_mrp_link-14.0.1.0.1.dev5.dist-info/WHEEL
odoo14_addon_stock_orderpoint_origin_mrp_link-14.0.1.0.1.dev5.dist-info/top_level.txt
odoo14_addon_stock_orderpoint_origin_mrp_link-14.0.1.0.1.dev5.dist-info/RECORD
