Metadata-Version: 2.1
Name: odoo14-addon-stock-orderpoint-origin-mrp-link
Version: 14.0.1.0.1.dev5
Summary: Link Purchase Orders to the replenishment demand MOs
Home-page: https://github.com/OCA/stock-logistics-warehouse
Author: Open Source Integrators, Odoo Community Association (OCA)
Author-email: support@odoo-community.org
License: LGPL-3
Platform: UNKNOWN
Classifier: Programming Language :: Python
Classifier: Framework :: Odoo
Classifier: Framework :: Odoo :: 14.0
Classifier: License :: OSI Approved :: GNU Lesser General Public License v3 (LGPLv3)
Requires-Python: >=3.6
Requires-Dist: odoo14-addon-stock-orderpoint-origin
Requires-Dist: odoo <14.1dev,>=14.0a
